how_short/__init__.py
how_short/how_short.py
how_short-0.1.1.dist-info/WHEEL
how_short-0.1.1.dist-info/METADATA
how_short-0.1.1.dist-info/RECORD
